govready_core/__init__.py
govready_core/bin/__init__.py
govready_core/bin/healthcheck.py
govready_core/environments/__init__.py
govready_core/environments/docker_compose/__init__.py
govready_core/environments/docker_compose/prompts.py
govready_core/environments/docker_compose/run.py
govready_core/environments/docker_compose/utils.py
govready_core-1.4.3.dist-info/LICENSE
govready_core-1.4.3.dist-info/METADATA
govready_core-1.4.3.dist-info/WHEEL
govready_core-1.4.3.dist-info/entry_points.txt
govready_core-1.4.3.dist-info/top_level.txt
govready_core-1.4.3.dist-info/RECORD
