Metadata-Version: 2.1
Name: govready-core
Version: 1.4.3
Summary: This is the Core module for GovReady products
Home-page: https://github.com/GovReady/govready-core
Author: Alexander Ward
Author-email: alexander.ward1@gmail.com
License: GNU
Platform: UNKNOWN
Classifier: License :: OSI Approved :: GNU General Public License v3 (GPLv3)
Classifier: Programming Language :: Python :: 3
Requires-Python: >=3.6
Requires-Dist: requests
Requires-Dist: pyyaml
